tumoroscope/__init__.py
tumoroscope/constants.py
tumoroscope/pre_processing.py
tumoroscope/run_simulation.py
tumoroscope/run_tumoroscope.py
tumoroscope/simulation.py
tumoroscope/tumoroscope.py
tumoroscope/visualization.py
tumoroscope-0.0.7.dist-info/METADATA
tumoroscope-0.0.7.dist-info/WHEEL
tumoroscope-0.0.7.dist-info/licenses/LICENSE
tumoroscope-0.0.7.dist-info/RECORD
