Metadata-Version: 2.1
Name: tumoroscope
Version: 0.0.7
Summary: Tumoroscope
Project-URL: Homepage, https://github.com/szczurek-lab/Tumoroscope
Project-URL: Bug Tracker, https://github.com/szczurek-lab/Tumoroscope/issues
Author-email: Shadi Darvish Shafighi <shafighi@mimuw.edu.pl>
License:                     GNU GENERAL PUBLIC LICENSE
License-File: LICENSE
Classifier: Operating System :: OS Independent
Classifier: Programming Language :: Python :: 3
Requires-Python: >=3.7
Requires-Dist: matplotlib>=3.1.2
Requires-Dist: numpy>=1.20.3
Requires-Dist: pandas>=1.3.5
Requires-Dist: pickle5>=0.0.11
Requires-Dist: scipy>=1.7.3
Requires-Dist: seaborn>=0.9.0
